{
  "indexes": [
    {
      "collectionGroup": "reverse_engineering_jobs",
      "queryScope": "COLLECTION",
      "fields": [
        { "fieldPath": "userId", "order": "ASCENDING" },
        { "fieldPath": "status", "order": "ASCENDING" }
      ]
    },
    {
      "collectionGroup": "user_api_keys",
      "queryScope": "COLLECTION",
      "fields": [
        { "fieldPath": "userId", "order": "ASCENDING" },
        { "fieldPath": "status", "order": "ASCENDING" }
      ]
    },
    {
      "collectionGroup": "user_api_keys",
      "queryScope": "COLLECTION",
      "fields": [
        { "fieldPath": "userId", "order": "ASCENDING" },
        { "fieldPath": "provider", "order": "ASCENDING" }
      ]
    },
    {
      "collectionGroup": "api_providers",
      "queryScope": "COLLECTION",
      "fields": [
        { "fieldPath": "active", "order": "ASCENDING" },
        { "fieldPath": "lastUsed", "order": "ASCENDING" }
      ]
    },
    {
      "collectionGroup": "api_providers",
      "queryScope": "COLLECTION",
      "fields": [
        { "fieldPath": "tier", "order": "ASCENDING" },
        { "fieldPath": "quotaUsed", "order": "ASCENDING" }
      ]
    },
    {
      "collectionGroup": "learning_entries",
      "queryScope": "COLLECTION",
      "fields": [
        { "fieldPath": "sessionId", "order": "ASCENDING" },
        { "fieldPath": "timestamp", "order": "ASCENDING" }
      ]
    },
    {
      "collectionGroup": "validation_results",
      "queryScope": "COLLECTION",
      "fields": [
        { "fieldPath": "taskId", "order": "ASCENDING" },
        { "fieldPath": "timestamp", "order": "DESCENDING" }
      ]
    },
    {
      "collectionGroup": "git_remotes",
      "queryScope": "COLLECTION",
      "fields": [
        { "fieldPath": "timestamp", "order": "DESCENDING" }
      ]
    }
  ],
  "fieldOverrides": []
}